pyimdf/__init__.py
pyimdf/__main__.py
pyimdf/app.py
pyimdf/imdf.py
pyimdf/imdf/__init__.py
pyimdf/imdf/footprint.py
pyimdf/imdf/venue.py
py_imdf-0.0.1.0.dist-info/AUTHORS.rst
py_imdf-0.0.1.0.dist-info/LICENSE.txt
py_imdf-0.0.1.0.dist-info/METADATA
py_imdf-0.0.1.0.dist-info/WHEEL
py_imdf-0.0.1.0.dist-info/top_level.txt
py_imdf-0.0.1.0.dist-info/RECORD
