Metadata-Version: 2.1
Name: py-imdf
Version: 0.0.1.0
Summary: QGIS to .IMDF conversion tool!
Home-page: https://pyscaffold.org/
Author: Lucas Selfslagh
Author-email: lucas.selfslagh@gmail.com
License: mit
Platform: any
Classifier: Development Status :: 4 - Beta
Classifier: Programming Language :: Python
Provides-Extra: testing
Requires-Dist: pytest ; extra == 'testing'
Requires-Dist: pytest-cov ; extra == 'testing'
